ruff_jupyter_jetbrains/__init__.py
ruff_jupyter_jetbrains/__main__.py
ruff_jupyter_jetbrains-1.0.0.dist-info/WHEEL
ruff_jupyter_jetbrains-1.0.0.dist-info/entry_points.txt
ruff_jupyter_jetbrains-1.0.0.dist-info/METADATA
ruff_jupyter_jetbrains-1.0.0.dist-info/RECORD
