Metadata-Version: 2.3
Name: ruff-jupyter-jetbrains
Version: 1.0.0
Summary: Add your description here
Requires-Dist: nbformat>=5.10.4
Requires-Python: >=3.10
Project-URL: Documentation, https://github.com/OliverSieweke/ruff-jupyter-jetbrains#readme
Project-URL: Homepage, https://github.com/OliverSieweke/ruff-jupyter-jetbrains
Project-URL: Issues, https://github.com/OliverSieweke/ruff-jupyter-jetbrains/issues
Project-URL: Repository, https://github.com/OliverSieweke/ruff-jupyter-jetbrains
